setup.py
thunctor/__init__.py
thunctor/thunctor.py
thunctor.egg-info/PKG-INFO
thunctor.egg-info/SOURCES.txt
thunctor.egg-info/dependency_links.txt
thunctor.egg-info/top_level.txt