Metadata-Version: 1.1
Name: thunctor
Version: 0.1.0
Summary: Safe recursion with monads
Home-page: https://github.com/mattneary/Thunctor
Author: Matt Neary
Author-email: neary.matt@gmail.com
License: Apache 2.0
Platform: UNKNOWN
Classifier: License :: OSI Approved :: Apache Software License
Classifier: Programming Language :: Python
